Metadata-Version: 2.1
Name: tb-mean-field-hubbard
Version: 2.0.1
Summary: Package to run tight-binding mean field hubbard calculations
Home-page: https://github.com/eimrek/tb-mean-field-hubbard
Author: Kristjan Eimre
Author-email: kristjaneimre@gmail.com
Classifier: Programming Language :: Python :: 3
Classifier: License :: OSI Approved :: MIT License
Classifier: Operating System :: OS Independent
Requires-Python: >=3.6
License-File: LICENSE
